{"nodes": [{"id": "quantpage_quantpage", "label": "QuantPage", "file_type": "code", "source_file": "/Users/shaurya555/Desktop/lazybull1/components/quant/QuantPage.tsx", "source_location": null, "source_url": null, "captured_at": null, "author": null, "contributor": null}, {"id": "quantpage_runall", "label": "runAll", "file_type": "code", "source_file": "/Users/shaurya555/Desktop/lazybull1/components/quant/QuantPage.tsx", "source_location": null, "source_url": null, "captured_at": null, "author": null, "contributor": null}, {"id": "quantpage_runone", "label": "runOne", "file_type": "code", "source_file": "/Users/shaurya555/Desktop/lazybull1/components/quant/QuantPage.tsx", "source_location": null, "source_url": null, "captured_at": null, "author": null, "contributor": null}, {"id": "quantpage_addbot", "label": "addBot", "file_type": "code", "source_file": "/Users/shaurya555/Desktop/lazybull1/components/quant/QuantPage.tsx", "source_location": null, "source_url": null, "captured_at": null, "author": null, "contributor": null}, {"id": "quantpage_importbot", "label": "importBot", "file_type": "code", "source_file": "/Users/shaurya555/Desktop/lazybull1/components/quant/QuantPage.tsx", "source_location": null, "source_url": null, "captured_at": null, "author": null, "contributor": null}, {"id": "quantpage_seedactive", "label": "seedActive", "file_type": "code", "source_file": "/Users/shaurya555/Desktop/lazybull1/components/quant/QuantPage.tsx", "source_location": null, "source_url": null, "captured_at": null, "author": null, "contributor": null}, {"id": "quantpage_buildtape", "label": "buildTape", "file_type": "code", "source_file": "/Users/shaurya555/Desktop/lazybull1/components/quant/QuantPage.tsx", "source_location": null, "source_url": null, "captured_at": null, "author": null, "contributor": null}, {"id": "quantpage_spotforsymbol", "label": "spotForSymbol", "file_type": "code", "source_file": "/Users/shaurya555/Desktop/lazybull1/components/quant/QuantPage.tsx", "source_location": null, "source_url": null, "captured_at": null, "author": null, "contributor": null}], "edges": [{"source": "quantpage_quantpage", "target": "quanthero_quanthero", "relation": "references", "confidence": "EXTRACTED", "confidence_score": 1.0, "source_file": "/Users/shaurya555/Desktop/lazybull1/components/quant/QuantPage.tsx", "source_location": null, "weight": 1.0}, {"source": "quantpage_quantpage", "target": "botlibrary_botlibrary", "relation": "references", "confidence": "EXTRACTED", "confidence_score": 1.0, "source_file": "/Users/shaurya555/Desktop/lazybull1/components/quant/QuantPage.tsx", "source_location": null, "weight": 1.0}, {"source": "quantpage_quantpage", "target": "workspace_workspace", "relation": "references", "confidence": "EXTRACTED", "confidence_score": 1.0, "source_file": "/Users/shaurya555/Desktop/lazybull1/components/quant/QuantPage.tsx", "source_location": null, "weight": 1.0}, {"source": "quantpage_quantpage", "target": "outputpanel_outputpanel", "relation": "references", "confidence": "EXTRACTED", "confidence_score": 1.0, "source_file": "/Users/shaurya555/Desktop/lazybull1/components/quant/QuantPage.tsx", "source_location": null, "weight": 1.0}, {"source": "quantpage_quantpage", "target": "importbotmodal_importbotmodal", "relation": "references", "confidence": "EXTRACTED", "confidence_score": 1.0, "source_file": "/Users/shaurya555/Desktop/lazybull1/components/quant/QuantPage.tsx", "source_location": null, "weight": 1.0}, {"source": "quantpage_quantpage", "target": "bots_botregistry", "relation": "references", "confidence": "EXTRACTED", "confidence_score": 1.0, "source_file": "/Users/shaurya555/Desktop/lazybull1/components/quant/QuantPage.tsx", "source_location": null, "weight": 1.0}, {"source": "quantpage_quantpage", "target": "quantpage_seedactive", "relation": "calls", "confidence": "EXTRACTED", "confidence_score": 1.0, "source_file": "/Users/shaurya555/Desktop/lazybull1/components/quant/QuantPage.tsx", "source_location": null, "weight": 1.0}, {"source": "quantpage_quantpage", "target": "quantpage_spotforsymbol", "relation": "calls", "confidence": "EXTRACTED", "confidence_score": 1.0, "source_file": "/Users/shaurya555/Desktop/lazybull1/components/quant/QuantPage.tsx", "source_location": null, "weight": 1.0}, {"source": "quantpage_quantpage", "target": "quantpage_buildtape", "relation": "calls", "confidence": "EXTRACTED", "confidence_score": 1.0, "source_file": "/Users/shaurya555/Desktop/lazybull1/components/quant/QuantPage.tsx", "source_location": null, "weight": 1.0}, {"source": "quantpage_quantpage", "target": "quantpage_runall", "relation": "calls", "confidence": "EXTRACTED", "confidence_score": 1.0, "source_file": "/Users/shaurya555/Desktop/lazybull1/components/quant/QuantPage.tsx", "source_location": null, "weight": 1.0}, {"source": "quantpage_quantpage", "target": "quantpage_runone", "relation": "calls", "confidence": "EXTRACTED", "confidence_score": 1.0, "source_file": "/Users/shaurya555/Desktop/lazybull1/components/quant/QuantPage.tsx", "source_location": null, "weight": 1.0}, {"source": "quantpage_quantpage", "target": "quantpage_addbot", "relation": "calls", "confidence": "EXTRACTED", "confidence_score": 1.0, "source_file": "/Users/shaurya555/Desktop/lazybull1/components/quant/QuantPage.tsx", "source_location": null, "weight": 1.0}, {"source": "quantpage_quantpage", "target": "quantpage_importbot", "relation": "calls", "confidence": "EXTRACTED", "confidence_score": 1.0, "source_file": "/Users/shaurya555/Desktop/lazybull1/components/quant/QuantPage.tsx", "source_location": null, "weight": 1.0}, {"source": "quantpage_seedactive", "target": "bots_getbot", "relation": "calls", "confidence": "EXTRACTED", "confidence_score": 1.0, "source_file": "/Users/shaurya555/Desktop/lazybull1/components/quant/QuantPage.tsx", "source_location": null, "weight": 1.0}, {"source": "quantpage_runall", "target": "types_botdef", "relation": "references", "confidence": "EXTRACTED", "confidence_score": 1.0, "source_file": "/Users/shaurya555/Desktop/lazybull1/components/quant/QuantPage.tsx", "source_location": null, "weight": 0.8}, {"source": "quantpage_importbot", "target": "quantpage_addbot", "relation": "calls", "confidence": "EXTRACTED", "confidence_score": 1.0, "source_file": "/Users/shaurya555/Desktop/lazybull1/components/quant/QuantPage.tsx", "source_location": null, "weight": 1.0}, {"source": "quantpage_quantpage", "target": "types_activebot", "relation": "shares_data_with", "confidence": "INFERRED", "confidence_score": 0.95, "source_file": "/Users/shaurya555/Desktop/lazybull1/components/quant/QuantPage.tsx", "source_location": null, "weight": 1.0}, {"source": "quantpage_quantpage", "target": "trade_page", "relation": "semantically_similar_to", "confidence": "INFERRED", "confidence_score": 0.75, "source_file": "/Users/shaurya555/Desktop/lazybull1/components/quant/QuantPage.tsx", "source_location": null, "weight": 0.7}, {"source": "quantpage_quantpage", "target": "pro_page", "relation": "semantically_similar_to", "confidence": "INFERRED", "confidence_score": 0.85, "source_file": "/Users/shaurya555/Desktop/lazybull1/components/quant/QuantPage.tsx", "source_location": null, "weight": 0.85}, {"source": "quantpage_quantpage", "target": "candles_generatecandles", "relation": "calls", "confidence": "EXTRACTED", "confidence_score": 1.0, "source_file": "/Users/shaurya555/Desktop/lazybull1/components/quant/QuantPage.tsx", "source_location": null, "weight": 1.0}], "hyperedges": [{"id": "workbench_three_column_layout", "label": "Quant workbench 3-column workspace layout", "nodes": ["botlibrary_botlibrary", "workspace_workspace", "outputpanel_outputpanel", "quantpage_quantpage"], "relation": "form", "confidence": "EXTRACTED", "confidence_score": 1.0, "source_file": "/Users/shaurya555/Desktop/lazybull1/components/quant/QuantPage.tsx"}]}